sphinx_iframes/__init__.py
sphinx_iframes/_version.py
sphinx_iframes/py.typed
sphinx_iframes-1.2.0.dist-info/METADATA
sphinx_iframes-1.2.0.dist-info/WHEEL
sphinx_iframes-1.2.0.dist-info/licenses/LICENSE
sphinx_iframes-1.2.0.dist-info/RECORD
