Metadata-Version: 2.4
Name: sphinx-iframes
Version: 1.2.0
Summary: A custom Sphinx extension to easily embed iframes in a Sphinx book
Author-email: Dennis den Ouden-van der Horst <d.denouden-vanderhorst@tudelft.nl>
License: MIT License
License-File: LICENSE
Requires-Python: >=3.10
Requires-Dist: sphinx
Requires-Dist: sphinx-metadata-figure>=v1.1.1
Requires-Dist: sphinxcontrib-video
